{"menus":[{"section":"External Pages","icon":"<i class=\"icon-home\"><\/i>","flag":"top-level","items":[{"name":"Dashboard","link":"\/","icon":"<i class=\"icon-home\"><\/i>"}]},{"section":"Pages","icon":"<i class=\"icon-docs\"><\/i>","flag":"dropdown","items":[{"name":"About","link":"\/about","icon":"<i class=\"icon-note\"><\/i>"},{"name":"Contact","link":"\/contact","icon":"<i class=\"icon-phone\"><\/i>"}]},{"section":"Users & Roles","icon":"<i class=\"icon-people\"><\/i>","flag":"dropdown","items":[{"name":"Users","link":"\/users","icon":"<i class=\"icon-people\"><\/i>"},{"name":"Roles","link":"\/roles","icon":"<i class=\"icon-key\"><\/i>"},{"name":"Permissions","link":"\/permissions","icon":"<i class=\"icon-lock-open\"><\/i>"}]},{"section":"Modules","icon":"<i class=\"icon-puzzle\"><\/i>","flag":"dropdown","items":[{"name":"Sample CRUD List","link":"\/samples","icon":"<i class=\"icon-puzzle\"><\/i>"},{"name":"Cat","link":"\/cat","icon":"<i class=\"icon-grid\"><\/i>"},{"name":"Cat","link":"\/cat","icon":"<i class=\"icon-grid\"><\/i>"},{"name":"Fire","link":"\/fire","icon":"<i class=\"icon-grid\"><\/i>"},{"name":"Cars","link":"\/cars","icon":"<i class=\"icon-grid\"><\/i>"},{"name":"Boots","link":"\/boots","icon":"<i class=\"icon-grid\"><\/i>"},{"name":"Elephants","link":"\/elephants","icon":"<i class=\"icon-grid\"><\/i>"},{"name":"Birds","link":"\/birds","icon":"<i class=\"icon-grid\"><\/i>"},{"name":"Flowers","link":"\/flowers","icon":"<i class=\"icon-grid\"><\/i>"},{"name":"Pots","link":"\/pots","icon":"<i class=\"icon-grid\"><\/i>"},{"name":"Trees","link":"\/trees","icon":"<i class=\"icon-grid\"><\/i>"},{"name":"Goats","link":"\/goats","icon":"<i class=\"icon-grid\"><\/i>"},{"name":"Cows","link":"\/cows","icon":"<i class=\"icon-grid\"><\/i>"},{"name":"Chickens","link":"\/chickens","icon":"<i class=\"icon-grid\"><\/i>"},{"name":"Frogs","link":"\/frogs","icon":"<i class=\"icon-grid\"><\/i>"},{"name":"Ants","link":"\/ants","icon":"<i class=\"icon-grid\"><\/i>"},{"name":"Bicycles","link":"\/bicycles","icon":"<i class=\"icon-grid\"><\/i>"}]},{"section":"Tools","icon":"<i class=\"icon-settings\"><\/i>","flag":"dropdown","items":[{"name":"CRUD Generator","link":"\/crud","icon":"<i class=\"icon-grid\"><\/i>"}]}]}